gitmuse/__init__.py
gitmuse/__main__.py
gitmuse/__version__.py
gitmuse/models.py
gitmuse/cli/__init__.py
gitmuse/cli/banner.py
gitmuse/cli/cli_core.py
gitmuse/cli/commands.py
gitmuse/cli/ui.py
gitmuse/config/__init__.py
gitmuse/config/gitmuse-schema.json
gitmuse/config/settings.py
gitmuse/core/__init__.py
gitmuse/core/diff_analyzer.py
gitmuse/core/git_utils.py
gitmuse/core/message_generator.py
gitmuse/providers/__init__.py
gitmuse/providers/base.py
gitmuse/providers/ollama.py
gitmuse/providers/openai.py
gitmuse/utils/check_hardware.py
gitmuse/utils/logging.py
gitmuse/utils/model_requirements.py
gitmuse-0.3.9.dist-info/METADATA
gitmuse-0.3.9.dist-info/WHEEL
gitmuse-0.3.9.dist-info/entry_points.txt
gitmuse-0.3.9.dist-info/licenses/LICENSE
gitmuse-0.3.9.dist-info/RECORD
