Metadata-Version: 2.3
Name: gitmuse
Version: 0.3.9
Summary: GitMuse is an AI-powered tool that helps developers craft meaningful and descriptive Git commit messages.
Project-URL: homepage, https://github.com/Arakiss/gitmuse
Project-URL: repository, https://github.com/Arakiss/gitmuse
Project-URL: documentation, https://github.com/Arakiss/gitmuse/wiki
Author-email: Petru Arakiss <petruarakiss@gmail.com>
License-Expression: MIT
License-File: LICENSE
Keywords: cli,commit-messages,git,gpt,openai,productivity
Classifier: Intended Audience :: Developers
Classifier: Intended Audience :: Information Technology
Classifier: Intended Audience :: System Administrators
Classifier: License :: OSI Approved :: MIT License
Classifier: Operating System :: OS Independent
Classifier: Programming Language :: Python :: 3
Classifier: Programming Language :: Python :: 3 :: Only
Classifier: Programming Language :: Python :: 3.11
Classifier: Topic :: Software Development
Requires-Python: >=3.11
Requires-Dist: click<9.0.0,>=8.1.7
Requires-Dist: jsonschema<5.0.0,>=4.23.0
Requires-Dist: ollama<0.4.0,>=0.3.0
Requires-Dist: openai<2.0.0,>=1.37.0
Requires-Dist: pydantic<3.0.0,>=2.8.2
Requires-Dist: requests<3.0.0,>=2.32.3
Requires-Dist: rich<14.0.0,>=13.1.0
Requires-Dist: ruff<0.6.0,>=0.5.4
Requires-Dist: structlog<25.0.0,>=24.4.0
Requires-Dist: toml<0.11.0,>=0.10.2
Provides-Extra: dev
Requires-Dist: mypy<2.0.0,>=1.11.0; extra == 'dev'
Requires-Dist: pytest<9.0.0,>=8.3.1; extra == 'dev'
Requires-Dist: types-jsonschema<5.0.0,>=4.23.0; extra == 'dev'
